aas2openapi_client/__init__.py
aas2openapi_client/api/__init__.py
aas2openapi_client/api/default/__init__.py
aas2openapi_client/api/default/root_get.py
aas2openapi_client/api/order/__init__.py
aas2openapi_client/api/order/delete_item_order_item_id_delete.py
aas2openapi_client/api/order/delete_item_order_item_id_order_schedule_delete.py
aas2openapi_client/api/order/delete_item_order_item_id_ordered_products_delete.py
aas2openapi_client/api/order/get_item_order_item_id_general_information_get.py
aas2openapi_client/api/order/get_item_order_item_id_get.py
aas2openapi_client/api/order/get_item_order_item_id_order_schedule_get.py
aas2openapi_client/api/order/get_item_order_item_id_ordered_products_get.py
aas2openapi_client/api/order/get_items_order_get.py
aas2openapi_client/api/order/post_item_order_item_id_order_schedule_post.py
aas2openapi_client/api/order/post_item_order_item_id_ordered_products_post.py
aas2openapi_client/api/order/post_item_order_post.py
aas2openapi_client/api/order/put_item_order_item_id_general_information_put.py
aas2openapi_client/api/order/put_item_order_item_id_order_schedule_put.py
aas2openapi_client/api/order/put_item_order_item_id_ordered_products_put.py
aas2openapi_client/api/order/put_item_order_item_id_put.py
aas2openapi_client/api/procedure/__init__.py
aas2openapi_client/api/procedure/delete_item_procedure_item_id_delete.py
aas2openapi_client/api/procedure/delete_item_procedure_item_id_execution_model_delete.py
aas2openapi_client/api/procedure/get_item_procedure_item_id_execution_model_get.py
aas2openapi_client/api/procedure/get_item_procedure_item_id_get.py
aas2openapi_client/api/procedure/get_item_procedure_item_id_procedure_information_get.py
aas2openapi_client/api/procedure/get_item_procedure_item_id_process_attributes_get.py
aas2openapi_client/api/procedure/get_item_procedure_item_id_time_model_get.py
aas2openapi_client/api/procedure/get_items_procedure_get.py
aas2openapi_client-0.2.2.dist-info/METADATA
aas2openapi_client-0.2.2.dist-info/WHEEL
aas2openapi_client-0.2.2.dist-info/RECORD
