Metadata-Version: 2.1
Name: aas2openapi-client
Version: 0.2.2
Summary: A client library for accessing aas2openapi
Requires-Python: >=3.8,<4.0
Classifier: Programming Language :: Python :: 3
Classifier: Programming Language :: Python :: 3.8
Classifier: Programming Language :: Python :: 3.9
Classifier: Programming Language :: Python :: 3.10
Classifier: Programming Language :: Python :: 3.11
Requires-Dist: attrs (>=21.3.0)
Requires-Dist: httpx (>=0.15.4,<0.25.0)
Requires-Dist: python-dateutil (>=2.8.0,<3.0.0)
